{
  "tasks": [
    {
      "name": "aaaa",
      "priority": "low",
      "status": "todo",
      "date": "1403/01/13 19:38:00",
      "id": 5418
    },
    {
      "name": "aab",
      "priority": "low",
      "status": "todo",
      "date": "1403/01/13 19:39:00",
      "id": 6594
    },
    {
      "name": "aac",
      "priority": "low",
      "status": "todo",
      "date": "1403/01/13 19:40:00",
      "id": 5760
    },
    {
      "name": "aad",
      "priority": "low",
      "status": "todo",
      "date": "1403/01/15 19:40:00",
      "id": 5031
    },
    {
      "name": "aae",
      "priority": "low",
      "status": "todo",
      "date": "1403/01/13 19:41:00",
      "id": 6775
    },
    {
      "name": "bbb",
      "priority": "low",
      "status": "todo",
      "date": "1403/01/13 19:42:00",
      "id": 83
    }
  ]
}